[
    {
        "dataset": "amazon-book",
        "seed": 42,
        "sparse_cov": 0.8333052276559865,
        "sparse_size": 9.07664418212479,
        "sparse_count": 11860,
        "medium_cov": 0.9191432747442192,
        "medium_size": 10.150695199190496,
        "medium_count": 53366,
        "rich_cov": 0.937757613498206,
        "rich_size": 11.778845298460991,
        "rich_count": 33723
    },
    {
        "dataset": "amazon-book",
        "seed": 43,
        "sparse_cov": 0.8956155143338954,
        "sparse_size": 47.916526138279934,
        "sparse_count": 11860,
        "medium_cov": 0.9043398418468688,
        "medium_size": 48.08895176704269,
        "medium_count": 53366,
        "rich_cov": 0.9188980814281055,
        "rich_size": 48.4688788067491,
        "rich_count": 33723
    },
    {
        "dataset": "amazon-book",
        "seed": 44,
        "sparse_cov": 0.8446037099494098,
        "sparse_size": 11.01231028667791,
        "sparse_count": 11860,
        "medium_cov": 0.9143462129445714,
        "medium_size": 12.1032305213057,
        "medium_count": 53366,
        "rich_cov": 0.9373721199181567,
        "rich_size": 14.300299498858346,
        "rich_count": 33723
    },
    {
        "dataset": "last-fm",
        "seed": 42,
        "sparse_cov": 0,
        "sparse_size": 0,
        "sparse_count": 0,
        "medium_cov": 0.9769126857423553,
        "medium_size": 8.838880019648778,
        "medium_count": 16286,
        "rich_cov": 0.9670669613461376,
        "rich_size": 8.624665062880165,
        "rich_count": 306774
    },
    {
        "dataset": "last-fm",
        "seed": 43,
        "sparse_cov": 0,
        "sparse_size": 0,
        "sparse_count": 0,
        "medium_cov": 0.9756232346800934,
        "medium_size": 8.792582586270417,
        "medium_count": 16286,
        "rich_cov": 0.9667996635960022,
        "rich_size": 8.633101240652728,
        "rich_count": 306774
    },
    {
        "dataset": "last-fm",
        "seed": 44,
        "sparse_cov": 0,
        "sparse_size": 0,
        "sparse_count": 0,
        "medium_cov": 0.9753162225224119,
        "medium_size": 8.865221662777847,
        "medium_count": 16286,
        "rich_cov": 0.9668713776265264,
        "rich_size": 8.684634291041613,
        "rich_count": 306774
    },
    {
        "dataset": "ml-1m",
        "seed": 42,
        "sparse_cov": 0,
        "sparse_size": 0,
        "sparse_count": 0,
        "medium_cov": 0.9615674453654861,
        "medium_size": 11.601356443104747,
        "medium_count": 1327,
        "rich_cov": 0.9021419741828277,
        "rich_size": 12.545595476928689,
        "rich_count": 98694
    },
    {
        "dataset": "ml-1m",
        "seed": 43,
        "sparse_cov": 0,
        "sparse_size": 0,
        "sparse_count": 0,
        "medium_cov": 0.9623210248681235,
        "medium_size": 11.09419743782969,
        "medium_count": 1327,
        "rich_cov": 0.9014631081930006,
        "rich_size": 12.074533406286097,
        "rich_count": 98694
    },
    {
        "dataset": "ml-1m",
        "seed": 44,
        "sparse_cov": 0,
        "sparse_size": 0,
        "sparse_count": 0,
        "medium_cov": 0.9645817633760362,
        "medium_size": 10.962321024868123,
        "medium_count": 1327,
        "rich_cov": 0.9013009909416986,
        "rich_size": 11.901463108193001,
        "rich_count": 98694
    }
]